imdb/__init__.py
imdb/__main__.py
imdb/api.py
imdb/imdb.py
p9q4-0.1.1.dist-info/LICENSE
p9q4-0.1.1.dist-info/METADATA
p9q4-0.1.1.dist-info/WHEEL
p9q4-0.1.1.dist-info/entry_points.txt
p9q4-0.1.1.dist-info/top_level.txt
p9q4-0.1.1.dist-info/RECORD
